{
  "$defs": {
    "bytebase.v1.ActuatorInfo.StatUser.jsonschema.strict.json": {
      "$schema": "https://json-schema.org/draft/2020-12/schema",
      "additionalProperties": false,
      "description": "User statistics by type and state.",
      "properties": {
        "count": {
          "description": "The count of users matching this type and state.",
          "maximum": 2147483647,
          "minimum": -2147483648,
          "type": "integer"
        },
        "state": {
          "description": "The state of the user.",
          "enum": [
            "STATE_UNSPECIFIED",
            "ACTIVE",
            "DELETED"
          ],
          "title": "State",
          "type": "string"
        },
        "userType": {
          "description": "The type of user.",
          "enum": [
            "USER_TYPE_UNSPECIFIED",
            "USER",
            "SYSTEM_BOT",
            "SERVICE_ACCOUNT"
          ],
          "title": "User Type",
          "type": "string"
        }
      },
      "required": [
        "userType",
        "state",
        "count"
      ],
      "title": "Stat User",
      "type": "object"
    },
    "bytebase.v1.ActuatorInfo.jsonschema.strict.json": {
      "$schema": "https://json-schema.org/draft/2020-12/schema",
      "additionalProperties": false,
      "description": "System information and configuration for the Bytebase instance.\n Actuator concept is similar to the Spring Boot Actuator.",
      "properties": {
        "activatedInstanceCount": {
          "description": "The number of activated database instances.",
          "maximum": 2147483647,
          "minimum": -2147483648,
          "type": "integer"
        },
        "debug": {
          "description": "Whether debug mode is enabled.",
          "type": "boolean"
        },
        "demo": {
          "description": "Whether the Bytebase instance is running in demo mode.",
          "type": "boolean"
        },
        "disallowPasswordSignin": {
          "description": "Whether password-based signin is disabled (except for workspace admins).",
          "type": "boolean"
        },
        "disallowSignup": {
          "description": "Whether self-service user signup is disabled.",
          "type": "boolean"
        },
        "docker": {
          "description": "Whether the Bytebase instance is running in Docker.",
          "type": "boolean"
        },
        "enableSample": {
          "description": "Whether sample data setup is enabled.",
          "type": "boolean"
        },
        "externalUrl": {
          "description": "The external URL where users or webhook callbacks access Bytebase.",
          "type": "string"
        },
        "externalUrlFromFlag": {
          "description": "Whether the external URL is set via command-line flag (and thus cannot be changed via UI).",
          "type": "boolean"
        },
        "gitCommit": {
          "description": "The git commit hash of the build.",
          "type": "string"
        },
        "host": {
          "description": "The host address of the Bytebase instance.",
          "type": "string"
        },
        "lastActiveTime": {
          "$ref": "#/$defs/google.protobuf.Timestamp.jsonschema.strict.json",
          "description": "The last time any API call was made, refreshed on each request."
        },
        "needAdminSetup": {
          "description": "Whether the Bytebase instance requires initial admin setup.",
          "type": "boolean"
        },
        "passwordRestriction": {
          "$ref": "#/$defs/bytebase.v1.WorkspaceProfileSetting.PasswordRestriction.jsonschema.strict.json",
          "description": "Password complexity and restriction requirements."
        },
        "port": {
          "description": "The port number of the Bytebase instance.",
          "type": "string"
        },
        "readonly": {
          "description": "Whether the Bytebase instance is running in read-only mode.",
          "type": "boolean"
        },
        "require2fa": {
          "description": "Whether two-factor authentication is required for all users.",
          "type": "boolean"
        },
        "saas": {
          "description": "Whether the Bytebase instance is running in SaaS mode where some features cannot be edited by users.",
          "type": "boolean"
        },
        "totalInstanceCount": {
          "description": "The total number of database instances.",
          "maximum": 2147483647,
          "minimum": -2147483648,
          "type": "integer"
        },
        "unlicensedFeatures": {
          "description": "List of features that are not licensed.",
          "items": {
            "type": "string"
          },
          "type": "array"
        },
        "userStats": {
          "description": "Statistics about users in the system.",
          "items": {
            "$ref": "#/$defs/bytebase.v1.ActuatorInfo.StatUser.jsonschema.strict.json"
          },
          "type": "array"
        },
        "version": {
          "description": "The Bytebase server version.",
          "type": "string"
        },
        "workspaceId": {
          "description": "The unique identifier for the workspace.",
          "type": "string"
        }
      },
      "required": [
        "version",
        "gitCommit",
        "readonly",
        "saas",
        "demo",
        "host",
        "port",
        "externalUrl",
        "needAdminSetup",
        "disallowSignup",
        "require2fa",
        "workspaceId",
        "debug",
        "disallowPasswordSignin",
        "docker",
        "activatedInstanceCount",
        "totalInstanceCount",
        "enableSample",
        "externalUrlFromFlag"
      ],
      "title": "Actuator Info",
      "type": "object"
    },
    "bytebase.v1.WorkspaceProfileSetting.PasswordRestriction.jsonschema.strict.json": {
      "$schema": "https://json-schema.org/draft/2020-12/schema",
      "additionalProperties": false,
      "properties": {
        "minLength": {
          "description": "min_length is the minimum length for password, should no less than 8.",
          "maximum": 2147483647,
          "minimum": -2147483648,
          "type": "integer"
        },
        "passwordRotation": {
          "$ref": "#/$defs/google.protobuf.Duration.jsonschema.strict.json",
          "description": "password_rotation requires users to reset their password after the duration."
        },
        "requireLetter": {
          "description": "require_letter requires the password must contains at least one letter, regardless of upper case or lower case",
          "type": "boolean"
        },
        "requireNumber": {
          "description": "require_number requires the password must contains at least one number.",
          "type": "boolean"
        },
        "requireResetPasswordForFirstLogin": {
          "description": "require_reset_password_for_first_login requires users to reset their password after the 1st login.",
          "type": "boolean"
        },
        "requireSpecialCharacter": {
          "description": "require_special_character requires the password must contains at least one special character.",
          "type": "boolean"
        },
        "requireUppercaseLetter": {
          "description": "require_uppercase_letter requires the password must contains at least one upper case letter.",
          "type": "boolean"
        }
      },
      "required": [
        "minLength",
        "requireNumber",
        "requireLetter",
        "requireUppercaseLetter",
        "requireSpecialCharacter",
        "requireResetPasswordForFirstLogin"
      ],
      "title": "Password Restriction",
      "type": "object"
    },
    "google.protobuf.Duration.jsonschema.strict.json": {
      "$schema": "https://json-schema.org/draft/2020-12/schema",
      "format": "duration",
      "title": "Duration",
      "type": "string"
    },
    "google.protobuf.Timestamp.jsonschema.strict.json": {
      "$schema": "https://json-schema.org/draft/2020-12/schema",
      "format": "date-time",
      "title": "Timestamp",
      "type": "string"
    }
  },
  "$id": "bytebase.v1.ActuatorInfo.jsonschema.strict.bundle.json",
  "$ref": "#/$defs/bytebase.v1.ActuatorInfo.jsonschema.strict.json",
  "$schema": "https://json-schema.org/draft/2020-12/schema"
}
