{
  "$defs": {
    "bytebase.v1.CreatePolicyRequest.schema.json": {
      "$schema": "https://json-schema.org/draft/2020-12/schema",
      "additionalProperties": false,
      "properties": {
        "parent": {
          "default": "",
          "description": "The parent resource where this instance will be created.\n Workspace resource name: \"\".\n Environment resource name: environments/environment-id.\n Instance resource name: instances/instance-id.\n Database resource name: instances/instance-id/databases/database-name.",
          "type": "string"
        },
        "policy": {
          "$ref": "#/$defs/bytebase.v1.Policy.schema.json",
          "description": "The policy to create."
        },
        "type": {
          "anyOf": [
            {
              "pattern": "^POLICY_TYPE_UNSPECIFIED$",
              "type": "string"
            },
            {
              "enum": [
                "ROLLOUT_POLICY",
                "MASKING_RULE",
                "MASKING_EXCEPTION",
                "TAG",
                "DATA_SOURCE_QUERY",
                "DATA_QUERY"
              ],
              "type": "string"
            },
            {
              "maximum": 2147483647,
              "minimum": -2147483648,
              "type": "integer"
            }
          ],
          "default": 0,
          "description": "The type of policy to create.",
          "title": "Policy Type"
        }
      },
      "title": "Create Policy Request",
      "type": "object"
    },
    "bytebase.v1.DataSourceQueryPolicy.schema.json": {
      "$schema": "https://json-schema.org/draft/2020-12/schema",
      "additionalProperties": false,
      "description": "Policy for controlling which data sources can be queried in the SQL editor.",
      "patternProperties": {
        "^(adminDataSourceRestriction)$": {
          "anyOf": [
            {
              "pattern": "^RESTRICTION_UNSPECIFIED$",
              "type": "string"
            },
            {
              "enum": [
                "FALLBACK",
                "DISALLOW"
              ],
              "type": "string"
            },
            {
              "maximum": 2147483647,
              "minimum": -2147483648,
              "type": "integer"
            }
          ],
          "default": 0,
          "description": "Restriction for admin data source queries.",
          "title": "Restriction"
        },
        "^(disallowDdl)$": {
          "default": false,
          "description": "Disallow running DDL statements in the SQL editor.",
          "type": "boolean"
        },
        "^(disallowDml)$": {
          "default": false,
          "description": "Disallow running DML statements in the SQL editor.",
          "type": "boolean"
        }
      },
      "properties": {
        "admin_data_source_restriction": {
          "anyOf": [
            {
              "pattern": "^RESTRICTION_UNSPECIFIED$",
              "type": "string"
            },
            {
              "enum": [
                "FALLBACK",
                "DISALLOW"
              ],
              "type": "string"
            },
            {
              "maximum": 2147483647,
              "minimum": -2147483648,
              "type": "integer"
            }
          ],
          "default": 0,
          "description": "Restriction for admin data source queries.",
          "title": "Restriction"
        },
        "disallow_ddl": {
          "default": false,
          "description": "Disallow running DDL statements in the SQL editor.",
          "type": "boolean"
        },
        "disallow_dml": {
          "default": false,
          "description": "Disallow running DML statements in the SQL editor.",
          "type": "boolean"
        }
      },
      "title": "Data Source Query Policy",
      "type": "object"
    },
    "bytebase.v1.MaskingExceptionPolicy.MaskingException.schema.json": {
      "$schema": "https://json-schema.org/draft/2020-12/schema",
      "additionalProperties": false,
      "description": "An exception allowing specific users to access masked data.",
      "properties": {
        "action": {
          "anyOf": [
            {
              "pattern": "^ACTION_UNSPECIFIED$",
              "type": "string"
            },
            {
              "enum": [
                "QUERY",
                "EXPORT"
              ],
              "type": "string"
            },
            {
              "maximum": 2147483647,
              "minimum": -2147483648,
              "type": "integer"
            }
          ],
          "default": 0,
          "description": "The action that the user can perform on sensitive data.",
          "title": "Action"
        },
        "condition": {
          "$ref": "#/$defs/google.type.Expr.schema.json",
          "description": "Support variables:\n resource.instance_id: the instance resource id. Only support \"==\" operation.\n resource.database_name: the database name. Only support \"==\" operation.\n resource.schema_name: the schema name. Only support \"==\" operation.\n resource.table_name: the table name. Only support \"==\" operation.\n resource.column_name: the column name. Only support \"==\" operation.\n request.time: the expiration. Only support \"\u003c\" operation in `request.time \u003c timestamp(\"{ISO datetime string format}\")`\n All variables should join with \"\u0026\u0026\" condition.\n\n For example:\n resource.instance_id == \"local\" \u0026\u0026 resource.database_name == \"employee\" \u0026\u0026 request.time \u003c timestamp(\"2025-04-30T11:10:39.000Z\")\n resource.instance_id == \"local\" \u0026\u0026 resource.database_name == \"employee\"",
          "title": "The condition that is associated with this exception policy instance.\n The syntax and semantics of CEL are documented at https://github.com/google/cel-spec\n If the condition is empty, means the user can access all databases without expiration."
        },
        "member": {
          "default": "",
          "description": "- `user:{email}`: An email address that represents a specific Bytebase account. For example, `alice@example.com`.\n - `group:{email}`: An email address for group.",
          "title": "Member is the principal who bind to this exception policy instance.",
          "type": "string"
        }
      },
      "title": "Masking Exception",
      "type": "object"
    },
    "bytebase.v1.MaskingExceptionPolicy.schema.json": {
      "$schema": "https://json-schema.org/draft/2020-12/schema",
      "additionalProperties": false,
      "description": "MaskingExceptionPolicy is the allowlist of users who can access sensitive data.",
      "patternProperties": {
        "^(maskingExceptions)$": {
          "description": "The list of masking exceptions.",
          "items": {
            "$ref": "#/$defs/bytebase.v1.MaskingExceptionPolicy.MaskingException.schema.json"
          },
          "type": "array"
        }
      },
      "properties": {
        "masking_exceptions": {
          "description": "The list of masking exceptions.",
          "items": {
            "$ref": "#/$defs/bytebase.v1.MaskingExceptionPolicy.MaskingException.schema.json"
          },
          "type": "array"
        }
      },
      "title": "Masking Exception Policy",
      "type": "object"
    },
    "bytebase.v1.MaskingRulePolicy.MaskingRule.schema.json": {
      "$schema": "https://json-schema.org/draft/2020-12/schema",
      "additionalProperties": false,
      "description": "A rule that defines when and how to mask data.",
      "patternProperties": {
        "^(semanticType)$": {
          "default": "",
          "description": "The semantic type of data to mask (e.g., \"SSN\", \"EMAIL\").",
          "type": "string"
        }
      },
      "properties": {
        "condition": {
          "$ref": "#/$defs/google.type.Expr.schema.json",
          "description": "Support variables:\n resource.environment_id: the environment resource id.\n resource.project_id: the project resource id.\n resource.instance_id: the instance resource id.\n resource.database_name: the database name.\n resource.table_name: the table name.\n resource.column_name: the column name.\n resource.classification_level: the classification level.\n\n Each variable support following operations:\n ==: the value equals the target.\n !=: the value not equals the target.\n in: the value matches one of the targets.\n !(in): the value not matches any of the targets.\n\n For example:\n resource.environment_id == \"test\" \u0026\u0026 resource.project_id == \"sample-project\"\n resource.instance_id == \"sample-instance\" \u0026\u0026 resource.database_name == \"employee\" \u0026\u0026 resource.table_name in [\"table1\", \"table2\"]\n resource.environment_id != \"test\" || !(resource.project_id in [\"poject1\", \"prject2\"])\n resource.instance_id == \"sample-instance\" \u0026\u0026 (resource.database_name == \"db1\" || resource.database_name == \"db2\")",
          "title": "The condition for the masking rule.\n The syntax and semantics of CEL are documented at https://github.com/google/cel-spec"
        },
        "id": {
          "default": "",
          "description": "A unique identifier for the rule in UUID format.",
          "type": "string"
        },
        "semantic_type": {
          "default": "",
          "description": "The semantic type of data to mask (e.g., \"SSN\", \"EMAIL\").",
          "type": "string"
        }
      },
      "title": "Masking Rule",
      "type": "object"
    },
    "bytebase.v1.MaskingRulePolicy.schema.json": {
      "$schema": "https://json-schema.org/draft/2020-12/schema",
      "additionalProperties": false,
      "description": "Policy for configuring data masking rules.",
      "properties": {
        "rules": {
          "description": "The list of masking rules.",
          "items": {
            "$ref": "#/$defs/bytebase.v1.MaskingRulePolicy.MaskingRule.schema.json"
          },
          "type": "array"
        }
      },
      "title": "Masking Rule Policy",
      "type": "object"
    },
    "bytebase.v1.Policy.schema.json": {
      "$schema": "https://json-schema.org/draft/2020-12/schema",
      "additionalProperties": false,
      "patternProperties": {
        "^(dataSourceQueryPolicy)$": {
          "$ref": "#/$defs/bytebase.v1.DataSourceQueryPolicy.schema.json"
        },
        "^(inheritFromParent)$": {
          "default": false,
          "description": "Whether this policy inherits from its parent resource.",
          "type": "boolean"
        },
        "^(maskingExceptionPolicy)$": {
          "$ref": "#/$defs/bytebase.v1.MaskingExceptionPolicy.schema.json"
        },
        "^(maskingRulePolicy)$": {
          "$ref": "#/$defs/bytebase.v1.MaskingRulePolicy.schema.json"
        },
        "^(queryDataPolicy)$": {
          "$ref": "#/$defs/bytebase.v1.QueryDataPolicy.schema.json"
        },
        "^(resourceType)$": {
          "anyOf": [
            {
              "pattern": "^RESOURCE_TYPE_UNSPECIFIED$",
              "type": "string"
            },
            {
              "enum": [
                "WORKSPACE",
                "ENVIRONMENT",
                "PROJECT"
              ],
              "type": "string"
            },
            {
              "maximum": 2147483647,
              "minimum": -2147483648,
              "type": "integer"
            }
          ],
          "default": 0,
          "description": "The resource type for the policy.",
          "title": "Policy Resource Type"
        },
        "^(rolloutPolicy)$": {
          "$ref": "#/$defs/bytebase.v1.RolloutPolicy.schema.json"
        },
        "^(tagPolicy)$": {
          "$ref": "#/$defs/bytebase.v1.TagPolicy.schema.json"
        }
      },
      "properties": {
        "data_source_query_policy": {
          "$ref": "#/$defs/bytebase.v1.DataSourceQueryPolicy.schema.json"
        },
        "enforce": {
          "default": false,
          "description": "Whether the policy is enforced.",
          "type": "boolean"
        },
        "inherit_from_parent": {
          "default": false,
          "description": "Whether this policy inherits from its parent resource.",
          "type": "boolean"
        },
        "masking_exception_policy": {
          "$ref": "#/$defs/bytebase.v1.MaskingExceptionPolicy.schema.json"
        },
        "masking_rule_policy": {
          "$ref": "#/$defs/bytebase.v1.MaskingRulePolicy.schema.json"
        },
        "name": {
          "default": "",
          "description": "The name of the policy.\n Format: {resource name}/policies/{policy type}\n Workspace resource name: \"\".\n Environment resource name: environments/environment-id.\n Instance resource name: instances/instance-id.\n Database resource name: instances/instance-id/databases/database-name.",
          "type": "string"
        },
        "query_data_policy": {
          "$ref": "#/$defs/bytebase.v1.QueryDataPolicy.schema.json"
        },
        "resource_type": {
          "anyOf": [
            {
              "pattern": "^RESOURCE_TYPE_UNSPECIFIED$",
              "type": "string"
            },
            {
              "enum": [
                "WORKSPACE",
                "ENVIRONMENT",
                "PROJECT"
              ],
              "type": "string"
            },
            {
              "maximum": 2147483647,
              "minimum": -2147483648,
              "type": "integer"
            }
          ],
          "default": 0,
          "description": "The resource type for the policy.",
          "title": "Policy Resource Type"
        },
        "rollout_policy": {
          "$ref": "#/$defs/bytebase.v1.RolloutPolicy.schema.json"
        },
        "tag_policy": {
          "$ref": "#/$defs/bytebase.v1.TagPolicy.schema.json"
        },
        "type": {
          "anyOf": [
            {
              "pattern": "^POLICY_TYPE_UNSPECIFIED$",
              "type": "string"
            },
            {
              "enum": [
                "ROLLOUT_POLICY",
                "MASKING_RULE",
                "MASKING_EXCEPTION",
                "TAG",
                "DATA_SOURCE_QUERY",
                "DATA_QUERY"
              ],
              "type": "string"
            },
            {
              "maximum": 2147483647,
              "minimum": -2147483648,
              "type": "integer"
            }
          ],
          "default": 0,
          "description": "The type of policy.",
          "title": "Policy Type"
        }
      },
      "title": "Policy",
      "type": "object"
    },
    "bytebase.v1.QueryDataPolicy.schema.json": {
      "$schema": "https://json-schema.org/draft/2020-12/schema",
      "additionalProperties": false,
      "description": "QueryDataPolicy is the policy configuration for querying data.",
      "patternProperties": {
        "^(disableCopyData)$": {
          "default": false,
          "description": "Disable copying query results.",
          "type": "boolean"
        },
        "^(disableExport)$": {
          "default": false,
          "description": "Disable data export in the SQL editor.",
          "type": "boolean"
        },
        "^(maximumResultRows)$": {
          "anyOf": [
            {
              "maximum": 2147483647,
              "minimum": -2147483648,
              "type": "integer"
            },
            {
              "pattern": "^-?[0-9]+$",
              "type": "string"
            }
          ],
          "default": 0,
          "description": "The maximum number of rows to return.\n The default value is -1, means no limit."
        },
        "^(maximumResultSize)$": {
          "anyOf": [
            {
              "type": "integer"
            },
            {
              "pattern": "^-?[0-9]+$",
              "type": "string"
            }
          ],
          "default": 0,
          "description": "The maximum result size limit in bytes.\n The default value is 100MB, we will use the default value if the setting not exists, or the limit \u003c= 0."
        }
      },
      "properties": {
        "disable_copy_data": {
          "default": false,
          "description": "Disable copying query results.",
          "type": "boolean"
        },
        "disable_export": {
          "default": false,
          "description": "Disable data export in the SQL editor.",
          "type": "boolean"
        },
        "maximum_result_rows": {
          "anyOf": [
            {
              "maximum": 2147483647,
              "minimum": -2147483648,
              "type": "integer"
            },
            {
              "pattern": "^-?[0-9]+$",
              "type": "string"
            }
          ],
          "default": 0,
          "description": "The maximum number of rows to return.\n The default value is -1, means no limit."
        },
        "maximum_result_size": {
          "anyOf": [
            {
              "type": "integer"
            },
            {
              "pattern": "^-?[0-9]+$",
              "type": "string"
            }
          ],
          "default": 0,
          "description": "The maximum result size limit in bytes.\n The default value is 100MB, we will use the default value if the setting not exists, or the limit \u003c= 0."
        },
        "timeout": {
          "$ref": "#/$defs/google.protobuf.Duration.schema.json",
          "description": "The query timeout duration."
        }
      },
      "title": "Query Data Policy",
      "type": "object"
    },
    "bytebase.v1.RolloutPolicy.Checkers.RequiredStatusChecks.schema.json": {
      "$schema": "https://json-schema.org/draft/2020-12/schema",
      "additionalProperties": false,
      "patternProperties": {
        "^(planCheckEnforcement)$": {
          "anyOf": [
            {
              "pattern": "^PLAN_CHECK_ENFORCEMENT_UNSPECIFIED$",
              "type": "string"
            },
            {
              "enum": [
                "ERROR_ONLY",
                "STRICT"
              ],
              "type": "string"
            },
            {
              "maximum": 2147483647,
              "minimum": -2147483648,
              "type": "integer"
            }
          ],
          "default": 0,
          "description": "Enforcement level for plan check results during rollout validation.",
          "title": "Plan Check Enforcement"
        }
      },
      "properties": {
        "plan_check_enforcement": {
          "anyOf": [
            {
              "pattern": "^PLAN_CHECK_ENFORCEMENT_UNSPECIFIED$",
              "type": "string"
            },
            {
              "enum": [
                "ERROR_ONLY",
                "STRICT"
              ],
              "type": "string"
            },
            {
              "maximum": 2147483647,
              "minimum": -2147483648,
              "type": "integer"
            }
          ],
          "default": 0,
          "description": "Enforcement level for plan check results during rollout validation.",
          "title": "Plan Check Enforcement"
        }
      },
      "title": "Required Status Checks",
      "type": "object"
    },
    "bytebase.v1.RolloutPolicy.Checkers.schema.json": {
      "$schema": "https://json-schema.org/draft/2020-12/schema",
      "additionalProperties": false,
      "patternProperties": {
        "^(requiredIssueApproval)$": {
          "default": false,
          "description": "Whether issue approval is required before proceeding with rollout.",
          "type": "boolean"
        },
        "^(requiredStatusChecks)$": {
          "$ref": "#/$defs/bytebase.v1.RolloutPolicy.Checkers.RequiredStatusChecks.schema.json",
          "description": "Status checks that must pass before rollout can be executed."
        }
      },
      "properties": {
        "required_issue_approval": {
          "default": false,
          "description": "Whether issue approval is required before proceeding with rollout.",
          "type": "boolean"
        },
        "required_status_checks": {
          "$ref": "#/$defs/bytebase.v1.RolloutPolicy.Checkers.RequiredStatusChecks.schema.json",
          "description": "Status checks that must pass before rollout can be executed."
        }
      },
      "title": "Checkers",
      "type": "object"
    },
    "bytebase.v1.RolloutPolicy.schema.json": {
      "$schema": "https://json-schema.org/draft/2020-12/schema",
      "additionalProperties": false,
      "description": "Rollout policy configuration.",
      "properties": {
        "automatic": {
          "default": false,
          "description": "Whether rollout is automatic without manual approval.",
          "type": "boolean"
        },
        "checkers": {
          "$ref": "#/$defs/bytebase.v1.RolloutPolicy.Checkers.schema.json",
          "description": "Checkers that must pass before rollout execution.\n These checks are performed in UI workflows only."
        },
        "roles": {
          "description": "The roles that can approve rollout execution.",
          "items": {
            "type": "string"
          },
          "type": "array"
        }
      },
      "title": "Rollout Policy",
      "type": "object"
    },
    "bytebase.v1.TagPolicy.schema.json": {
      "$schema": "https://json-schema.org/draft/2020-12/schema",
      "additionalProperties": false,
      "description": "Policy for tagging resources with metadata.",
      "properties": {
        "tags": {
          "additionalProperties": {
            "type": "string"
          },
          "description": "tags is the key - value map for resources.\n for example, the environment resource can have the sql review config tag, like \"bb.tag.review_config\": \"reviewConfigs/{review config resource id}\"",
          "propertyNames": {
            "type": "string"
          },
          "type": "object"
        }
      },
      "title": "Tag Policy",
      "type": "object"
    },
    "google.protobuf.Duration.schema.json": {
      "$schema": "https://json-schema.org/draft/2020-12/schema",
      "format": "duration",
      "title": "Duration",
      "type": "string"
    },
    "google.type.Expr.schema.json": {
      "$schema": "https://json-schema.org/draft/2020-12/schema",
      "additionalProperties": false,
      "description": "Example (Comparison):\n\n     title: \"Summary size limit\"\n     description: \"Determines if a summary is less than 100 chars\"\n     expression: \"document.summary.size() \u003c 100\"\n\n Example (Equality):\n\n     title: \"Requestor is owner\"\n     description: \"Determines if requestor is the document owner\"\n     expression: \"document.owner == request.auth.claims.email\"\n\n Example (Logic):\n\n     title: \"Public documents\"\n     description: \"Determine whether the document should be publicly visible\"\n     expression: \"document.type != 'private' \u0026\u0026 document.type != 'internal'\"\n\n Example (Data Manipulation):\n\n     title: \"Notification string\"\n     description: \"Create a notification string with a timestamp.\"\n     expression: \"'New message received at ' + string(document.create_time)\"\n\n The exact variables and functions that may be referenced within an expression\n are determined by the service that evaluates it. See the service\n documentation for additional information.",
      "properties": {
        "description": {
          "default": "",
          "description": "Optional. Description of the expression. This is a longer text which\n describes the expression, e.g. when hovered over it in a UI.",
          "type": "string"
        },
        "expression": {
          "default": "",
          "description": "Textual representation of an expression in Common Expression Language\n syntax.",
          "type": "string"
        },
        "location": {
          "default": "",
          "description": "Optional. String indicating the location of the expression for error\n reporting, e.g. a file name and a position in the file.",
          "type": "string"
        },
        "title": {
          "default": "",
          "description": "Optional. Title for the expression, i.e. a short string describing\n its purpose. This can be used e.g. in UIs which allow to enter the\n expression.",
          "type": "string"
        }
      },
      "title": "Represents a textual expression in the Common Expression Language (CEL)\n syntax. CEL is a C-like expression language. The syntax and semantics of CEL\n are documented at https://github.com/google/cel-spec.",
      "type": "object"
    }
  },
  "$id": "bytebase.v1.CreatePolicyRequest.schema.bundle.json",
  "$ref": "#/$defs/bytebase.v1.CreatePolicyRequest.schema.json",
  "$schema": "https://json-schema.org/draft/2020-12/schema"
}
