{
  "$id": "bytebase.v1.TessellationConfig.schema.json",
  "$schema": "https://json-schema.org/draft/2020-12/schema",
  "additionalProperties": false,
  "description": "TessellationConfig defines tessellation parameters for spatial indexes.",
  "patternProperties": {
    "^(boundingBox)$": {
      "$ref": "bytebase.v1.BoundingBox.schema.json",
      "description": "Bounding box for GEOMETRY tessellation (not used for GEOGRAPHY)"
    },
    "^(cellsPerObject)$": {
      "anyOf": [
        {
          "maximum": 2147483647,
          "minimum": -2147483648,
          "type": "integer"
        },
        {
          "pattern": "^-?[0-9]+$",
          "type": "string"
        }
      ],
      "default": 0,
      "description": "Number of cells per object (1-8192 for SQL Server)"
    },
    "^(gridLevels)$": {
      "description": "Grid levels and densities for multi-level tessellation",
      "items": {
        "$ref": "bytebase.v1.GridLevel.schema.json"
      },
      "type": "array"
    }
  },
  "properties": {
    "bounding_box": {
      "$ref": "bytebase.v1.BoundingBox.schema.json",
      "description": "Bounding box for GEOMETRY tessellation (not used for GEOGRAPHY)"
    },
    "cells_per_object": {
      "anyOf": [
        {
          "maximum": 2147483647,
          "minimum": -2147483648,
          "type": "integer"
        },
        {
          "pattern": "^-?[0-9]+$",
          "type": "string"
        }
      ],
      "default": 0,
      "description": "Number of cells per object (1-8192 for SQL Server)"
    },
    "grid_levels": {
      "description": "Grid levels and densities for multi-level tessellation",
      "items": {
        "$ref": "bytebase.v1.GridLevel.schema.json"
      },
      "type": "array"
    },
    "scheme": {
      "default": "",
      "description": "Tessellation scheme (e.g., \"GEOMETRY_GRID\", \"GEOGRAPHY_GRID\", \"GEOMETRY_AUTO_GRID\")",
      "type": "string"
    }
  },
  "title": "Tessellation Config",
  "type": "object"
}
